{
	"configurations" : 
	[
		{
			"directories" : 
			[
				{
					"build" : ".",
					"hasInstallRule" : true,
					"jsonFile" : "directory-.-Debug-9ede57218272f6e22b25.json",
					"minimumCMakeVersion" : 
					{
						"string" : "3.5"
					},
					"projectIndex" : 0,
					"source" : ".",
					"targetIndexes" : 
					[
						0
					]
				}
			],
			"name" : "Debug",
			"projects" : 
			[
				{
					"directoryIndexes" : 
					[
						0
					],
					"name" : "QT_karkit",
					"targetIndexes" : 
					[
						0
					]
				}
			],
			"targets" : 
			[
				{
					"directoryIndex" : 0,
					"id" : "QT_karkit::@6890427a1f51a3e7e1df",
					"jsonFile" : "target-QT_karkit-Debug-8701bb84eef702f91e90.json",
					"name" : "QT_karkit",
					"projectIndex" : 0
				}
			]
		}
	],
	"kind" : "codemodel",
	"paths" : 
	{
		"build" : "C:/Users/henri/Google Drive/Coding/Qt_Harjoitukset/QT_karkit/build",
		"source" : "C:/Users/henri/Google Drive/Coding/Qt_Harjoitukset/QT_karkit"
	},
	"version" : 
	{
		"major" : 2,
		"minor" : 4
	}
}
